MANIFEST.in
README.txt
setup.cfg
setup.py
docs/HISTORY.txt
docs/INSTALL.txt
docs/LICENSE.GPL
docs/LICENSE.txt
redomino/__init__.py
redomino/__init__.pyc
redomino.keywordalias.egg-info/PKG-INFO
redomino.keywordalias.egg-info/SOURCES.txt
redomino.keywordalias.egg-info/dependency_links.txt
redomino.keywordalias.egg-info/entry_points.txt
redomino.keywordalias.egg-info/namespace_packages.txt
redomino.keywordalias.egg-info/not-zip-safe
redomino.keywordalias.egg-info/requires.txt
redomino.keywordalias.egg-info/top_level.txt
redomino/keywordalias/__init__.py
redomino/keywordalias/configure.zcml
redomino/keywordalias/i18n.sh
redomino/keywordalias/interfaces.py
redomino/keywordalias/tests.py
redomino/keywordalias/utils.py
redomino/keywordalias/browser/__init__.py
redomino/keywordalias/browser/configure.zcml
redomino/keywordalias/browser/interfaces.py
redomino/keywordalias/browser/keywordtranslator.py
redomino/keywordalias/browser/managekeywords.py
redomino/keywordalias/browser/widgets.py
redomino/keywordalias/browser/widgets.zcml
redomino/keywordalias/browser/resources/icontool.png
redomino/keywordalias/browser/resources/keywordalias.css
redomino/keywordalias/browser/templates/checkbox_input.pt
redomino/keywordalias/browser/templates/filedunder.pt
redomino/keywordalias/browser/templates/keywordlangkey_display.pt
redomino/keywordalias/browser/templates/keywords.pt
redomino/keywordalias/browser/templates/multiselectkeywords.pt
redomino/keywordalias/locales/redomino.keywordalias.pot
redomino/keywordalias/locales/en/LC_MESSAGES/redomino.keywordalias.po
redomino/keywordalias/locales/it/LC_MESSAGES/redomino.keywordalias.po
redomino/keywordalias/profiles/default/browserlayer.xml
redomino/keywordalias/profiles/default/controlpanel.xml
redomino/keywordalias/profiles/default/cssregistry.xml
redomino/keywordalias/profiles/default/metadata.xml
redomino/keywordalias/profiles/default/registry.xml