Metadata-Version: 1.1
Name: redomino.keywordalias
Version: 0.1
Summary: Keyword alias
Home-page: https://github.com/redomino/redomino.keywordalias
Author: Davide Moro
Author-email: davide.moro@redomino.com
License: GPL
Platform: UNKNOWN
Classifier: Framework :: Plone
Classifier: Programming Language :: Python
